README.rst
setup.py
quickemailverification/__init__.py
quickemailverification/client.py
quickemailverification.egg-info/PKG-INFO
quickemailverification.egg-info/SOURCES.txt
quickemailverification.egg-info/dependency_links.txt
quickemailverification.egg-info/requires.txt
quickemailverification.egg-info/top_level.txt
quickemailverification/api/__init__.py
quickemailverification/api/quickemailverification.py
quickemailverification/error/__init__.py
quickemailverification/error/client_error.py
quickemailverification/http_client/__init__.py
quickemailverification/http_client/auth_handler.py
quickemailverification/http_client/error_handler.py
quickemailverification/http_client/request_handler.py
quickemailverification/http_client/response.py
quickemailverification/http_client/response_handler.py