Metadata-Version: 1.1
Name: quickemailverification
Version: 1.0.1
Summary: Official QuickEmailVerification API library client for python
Home-page: https://github.com/quickemailverification/quickemailverification-python
Author: QuickEmailVerification
Author-email: support@quickemailverification.com
License: MIT
Platform: UNKNOWN
Classifier: Development Status :: 5 - Production/Stable
Classifier: Intended Audience :: Developers
Classifier: License :: OSI Approved :: MIT License
Classifier: Operating System :: OS Independent
Classifier: Programming Language :: Python :: 2.6
Classifier: Programming Language :: Python :: 2.7
Classifier: Programming Language :: Python :: 3.2
Classifier: Programming Language :: Python :: 3.3
Classifier: Programming Language :: Python :: 3.4
Classifier: Topic :: Software Development :: Libraries :: Python Modules
